nbconvert/__init__.py
nbconvert/__main__.py
nbconvert/_version.py
nbconvert/conftest.py
nbconvert/nbconvertapp.py
nbconvert/py.typed
nbconvert/exporters/__init__.py
nbconvert/exporters/asciidoc.py
nbconvert/exporters/base.py
nbconvert/exporters/exporter.py
nbconvert/exporters/html.py
nbconvert/exporters/latex.py
nbconvert/exporters/markdown.py
nbconvert/exporters/notebook.py
nbconvert/exporters/pdf.py
nbconvert/exporters/python.py
nbconvert/exporters/qt_exporter.py
nbconvert/exporters/qt_screenshot.py
nbconvert/exporters/qtpdf.py
nbconvert/exporters/qtpng.py
nbconvert/exporters/rst.py
nbconvert/exporters/script.py
nbconvert/exporters/slides.py
nbconvert/exporters/templateexporter.py
nbconvert/exporters/webpdf.py
nbconvert/filters/__init__.py
nbconvert/filters/ansi.py
nbconvert/filters/citation.py
nbconvert/filters/datatypefilter.py
nbconvert/filters/filter_links.py
nbconvert/filters/highlight.py
nbconvert/filters/latex.py
nbconvert/filters/markdown.py
nbconvert/filters/markdown_mistune.py
nbconvert/filters/metadata.py
nbconvert/filters/pandoc.py
nbconvert/filters/strings.py
nbconvert/filters/widgetsdatatypefilter.py
nbconvert/postprocessors/__init__.py
nbconvert/postprocessors/base.py
nbconvert/postprocessors/serve.py
nbconvert/preprocessors/__init__.py
nbconvert/preprocessors/base.py
nbconvert/preprocessors/clearmetadata.py
nbconvert/preprocessors/clearoutput.py
nbconvert/preprocessors/coalescestreams.py
nbconvert/preprocessors/convertfigures.py
nbconvert/preprocessors/csshtmlheader.py
nbconvert/preprocessors/execute.py
nbconvert/preprocessors/extractattachments.py
nbconvert/preprocessors/extractoutput.py
nbconvert/preprocessors/highlightmagics.py
nbconvert/preprocessors/latex.py
nbconvert/preprocessors/regexremove.py
nbconvert/preprocessors/sanitize.py
nbconvert/preprocessors/svg2pdf.py
nbconvert/preprocessors/tagremove.py
nbconvert/resources/__init__.py
nbconvert/templates/README.md
nbconvert/templates/skeleton/Makefile
nbconvert/templates/skeleton/README.md
nbconvert-7.16.3.dist-info/METADATA
nbconvert-7.16.3.dist-info/WHEEL
nbconvert-7.16.3.dist-info/entry_points.txt
nbconvert-7.16.3.dist-info/licenses/LICENSE
nbconvert-7.16.3.dist-info/RECORD
