Metadata-Version: 2.3
Name: nbconvert
Version: 7.16.3
Summary: Converting Jupyter Notebooks (.ipynb files) to other formats.  Output formats include asciidoc, html, latex, markdown, pdf, py, rst, script.  nbconvert can be used both as a Python library (`import nbconvert`) or as a command line tool (invoked as `jupyter nbconvert ...`).
Project-URL: Homepage, https://jupyter.org
Author-email: Jupyter Development Team <jupyter@googlegroups.com>
License: BSD 3-Clause License
License-File: LICENSE
Keywords: Interactive,Interpreter,Shell,Web
Classifier: Intended Audience :: Developers
Classifier: Intended Audience :: Science/Research
Classifier: Intended Audience :: System Administrators
Classifier: License :: OSI Approved :: BSD License
Classifier: Programming Language :: Python
Classifier: Programming Language :: Python :: 3
Requires-Python: >=3.8
Requires-Dist: beautifulsoup4
Requires-Dist: bleach!=5.0.0
Requires-Dist: defusedxml
Requires-Dist: importlib-metadata>=3.6; python_version < '3.10'
Requires-Dist: jinja2>=3.0
Requires-Dist: jupyter-core>=4.7
Requires-Dist: jupyterlab-pygments
Requires-Dist: markupsafe>=2.0
Requires-Dist: mistune<4,>=2.0.3
Requires-Dist: nbclient>=0.5.0
Requires-Dist: nbformat>=5.7
Requires-Dist: packaging
Requires-Dist: pandocfilters>=1.4.1
Requires-Dist: pygments>=2.4.1
Requires-Dist: tinycss2
Requires-Dist: traitlets>=5.1
Provides-Extra: all
Requires-Dist: nbconvert[docs,qtpdf,serve,test,webpdf]; extra == 'all'
Provides-Extra: docs
Requires-Dist: ipykernel; extra == 'docs'
Requires-Dist: ipython; extra == 'docs'
Requires-Dist: myst-parser; extra == 'docs'
Requires-Dist: nbsphinx>=0.2.12; extra == 'docs'
Requires-Dist: pydata-sphinx-theme; extra == 'docs'
Requires-Dist: sphinx==5.0.2; extra == 'docs'
Requires-Dist: sphinxcontrib-spelling; extra == 'docs'
Provides-Extra: qtpdf
Requires-Dist: nbconvert[qtpng]; extra == 'qtpdf'
Provides-Extra: qtpng
Requires-Dist: pyqtwebengine>=5.15; extra == 'qtpng'
Provides-Extra: serve
Requires-Dist: tornado>=6.1; extra == 'serve'
Provides-Extra: test
Requires-Dist: flaky; extra == 'test'
Requires-Dist: ipykernel; extra == 'test'
Requires-Dist: ipywidgets>=7.5; extra == 'test'
Requires-Dist: pytest>=7; extra == 'test'
Provides-Extra: webpdf
Requires-Dist: playwright; extra == 'webpdf'
